salesforce_dbsync/__init__.py
salesforce_dbsync/class_MySQL_Helper.py
salesforce_dbsync/class_SFDC_Helper.py
salesforce_dbsync/class_Sync_Manager.py
salesforce_dbsync-1.4.4.dist-info/LICENSE
salesforce_dbsync-1.4.4.dist-info/METADATA
salesforce_dbsync-1.4.4.dist-info/WHEEL
salesforce_dbsync-1.4.4.dist-info/top_level.txt
salesforce_dbsync-1.4.4.dist-info/RECORD
