Metadata-Version: 2.1
Name: salesforce-dbsync
Version: 1.4.4
Summary: Python library to download data from Salesforce and synchronize with a relational database
Home-page: https://github.com/satapathy/pypi-salesforce-dbsync
Author: S Satapathy
Author-email: shubhakant.satapathy@gmail.com
License: UNKNOWN
Platform: UNKNOWN
Classifier: Programming Language :: Python :: 3
Classifier: License :: OSI Approved :: MIT License
Classifier: Operating System :: OS Independent
Requires-Dist: simple-salesforce
Requires-Dist: mysql.connector
Requires-Dist: screenwriter
